Metadata-Version: 2.1
Name: frame-model
Version: 0.1.2
Summary: Módulo para distribuição de Modelos Numéricos.
Home-page: https://github.com/framework-CPTEC/
Author: Framework
Author-email: frameworkcptec@gmail.com
License: MIT
Project-URL: Código fonte, https://github.com/framework-CPTEC/
Project-URL: Download, https://github.com/framework-CPTEC/
Keywords: recuperação de dados climáticos
Classifier: Development Status :: 5 - Production/Stable
Classifier: Intended Audience :: Developers
Classifier: License :: OSI Approved :: MIT License
Classifier: Natural Language :: Portuguese (Brazilian)
Classifier: Operating System :: OS Independent
Classifier: Topic :: Software Development :: Internationalization
Classifier: Topic :: Scientific/Engineering :: Physics
Requires-Python: >=3.10
License-File: LICENSE
